CONTRIBUTORS.rst
LICENSE
MANIFEST.in
README.rst
setup.py
awesome_bootstrap/__init__.py
awesome_bootstrap/models.py
awesome_bootstrap/static/font_awesome/css/font-awesome.css
awesome_bootstrap/static/font_awesome/css/font-awesome.min.css
awesome_bootstrap/static/font_awesome/fonts/FontAwesome.otf
awesome_bootstrap/static/font_awesome/fonts/fontawesome-webfont.eot
awesome_bootstrap/static/font_awesome/fonts/fontawesome-webfont.svg
awesome_bootstrap/static/font_awesome/fonts/fontawesome-webfont.ttf
awesome_bootstrap/static/font_awesome/fonts/fontawesome-webfont.woff
awesome_bootstrap/static/font_awesome/less/bordered-pulled.less
awesome_bootstrap/static/font_awesome/less/core.less
awesome_bootstrap/static/font_awesome/less/extras.less
awesome_bootstrap/static/font_awesome/less/fixed-width.less
awesome_bootstrap/static/font_awesome/less/font-awesome.less
awesome_bootstrap/static/font_awesome/less/icons.less
awesome_bootstrap/static/font_awesome/less/larger.less
awesome_bootstrap/static/font_awesome/less/list.less
awesome_bootstrap/static/font_awesome/less/mixins.less
awesome_bootstrap/static/font_awesome/less/path.less
awesome_bootstrap/static/font_awesome/less/rotated-flipped.less
awesome_bootstrap/static/font_awesome/less/spinning.less
awesome_bootstrap/static/font_awesome/less/stacked.less
awesome_bootstrap/static/font_awesome/less/variables.less
awesome_bootstrap/static/twitter_bootstrap/dist/css/bootstrap-theme.css
awesome_bootstrap/static/twitter_bootstrap/dist/css/bootstrap-theme.css.map
awesome_bootstrap/static/twitter_bootstrap/dist/css/bootstrap-theme.min.css
awesome_bootstrap/static/twitter_bootstrap/dist/css/bootstrap.css
awesome_bootstrap/static/twitter_bootstrap/dist/css/bootstrap.css.map
awesome_bootstrap/static/twitter_bootstrap/dist/css/bootstrap.min.css
awesome_bootstrap/static/twitter_bootstrap/dist/fonts/glyphicons-halflings-regular.eot
awesome_bootstrap/static/twitter_bootstrap/dist/fonts/glyphicons-halflings-regular.svg
django_awesome_bootstrap.egg-info/PKG-INFO
django_awesome_bootstrap.egg-info/SOURCES.txt
django_awesome_bootstrap.egg-info/dependency_links.txt
django_awesome_bootstrap.egg-info/top_level.txt