Metadata-Version: 1.1
Name: django-awesome-bootstrap
Version: 3.2.0
Summary: A Django app for including twitter bootstrap and font awesome.
Home-page: https://github.com/infoagetech/django-awesome-bootstrap
Author: Troy Grosfield
Author-email: UNKNOWN
License: MIT License
Download-URL: https://pypi.python.org/pypi/django-awesome-bootstrap
Platform: UNKNOWN
Classifier: Environment :: Web Environment
Classifier: Framework :: Django
Classifier: Intended Audience :: Developers
Classifier: License :: OSI Approved :: MIT License
Classifier: Operating System :: OS Independent
Classifier: Programming Language :: Python
Classifier: Topic :: Internet :: WWW/HTTP
Classifier: Topic :: Internet :: WWW/HTTP :: Dynamic Content
